keytoppyutils-2.5.2.7.dist-info/licenses/LICENSE
kt_base/CommonUtils.py
kt_base/FileUtils.py
kt_base/ObsUtils.py
kt_base/__init__.py
kt_text/AlignTickLabelsUtils.py
kt_text/BarAndLineChartUtils.py
kt_text/BarChartUtils.py
kt_text/ChartGenerator.py
kt_text/Config.py
kt_text/FillLineChartUtils.py
kt_text/LineChartUtils.py
kt_text/MarkdownConverter.py
kt_text/RingChartUtils.py
kt_text/__init__.py
keytoppyutils-2.5.2.7.dist-info/METADATA
keytoppyutils-2.5.2.7.dist-info/WHEEL
keytoppyutils-2.5.2.7.dist-info/top_level.txt
keytoppyutils-2.5.2.7.dist-info/RECORD
