Metadata-Version: 2.4
Name: keytopPyUtils
Version: 2.5.2.7
Summary: keytop python utils
Home-page: 
Author: zhangjukai
Author-email: zhangjukai@keytop.com.cn
Classifier: Programming Language :: Python :: 3
Classifier: License :: OSI Approved :: MIT License
Classifier: Operating System :: OS Independent
Requires-Python: >=3.6
License-File: LICENSE
Requires-Dist: markdown
Requires-Dist: bs4
Requires-Dist: python-docx
Requires-Dist: weasyprint==52.5
Requires-Dist: esdk-obs-python
Requires-Dist: matplotlib
Dynamic: author
Dynamic: author-email
Dynamic: classifier
Dynamic: description
Dynamic: description-content-type
Dynamic: license-file
Dynamic: requires-dist
Dynamic: requires-python
Dynamic: summary
